cargos_api/__init__.py
cargos_api/api.py
cargos_api/exceptions.py
cargos_api/locations_loader.py
cargos_api/mapper.py
cargos_api/models.py
cargos_api/data/luoghi.csv
cargos_api/data/tipo_documento.csv
cargos_api/data/tipo_pagamento.csv
cargos_api/data/tipo_veicolo.csv
cargos_api-0.2.4.dist-info/METADATA
cargos_api-0.2.4.dist-info/WHEEL
cargos_api-0.2.4.dist-info/top_level.txt
cargos_api-0.2.4.dist-info/RECORD
