Metadata-Version: 2.4
Name: cargos-api
Version: 0.2.4
Summary: Python client and strict mapper for the Italian Police Ca.R.G.O.S. API
Author-email: glizzykingdreko <glizzykingdreko@protonamail.com>
License: MIT
Project-URL: Homepage, https://github.com/GlizzyKingDreko/cargos-api
Keywords: cargos,poliziadistato,italy,api,rentals
Requires-Python: >=3.9
Requires-Dist: requests>=2.28
Requires-Dist: pycryptodome>=3.19
